LICENSE
MANIFEST.in
README.md
VERSION
pyproject.toml
requirements-client.txt
requirements.txt
setup.py
covalent/__init__.py
covalent/py.typed
covalent.egg-info/PKG-INFO
covalent.egg-info/SOURCES.txt
covalent.egg-info/dependency_links.txt
covalent.egg-info/entry_points.txt
covalent.egg-info/not-zip-safe
covalent.egg-info/requires.txt
covalent.egg-info/top_level.txt
covalent/_api/__init__.py
covalent/_api/apiclient.py
covalent/_dispatcher_plugins/__init__.py
covalent/_dispatcher_plugins/base.py
covalent/_dispatcher_plugins/local.py
covalent/_file_transfer/__init__.py
covalent/_file_transfer/enums.py
covalent/_file_transfer/file.py
covalent/_file_transfer/file_transfer.py
covalent/_file_transfer/folder.py
covalent/_file_transfer/strategies/__init__.py
covalent/_file_transfer/strategies/blob_strategy.py
covalent/_file_transfer/strategies/gcloud_strategy.py
covalent/_file_transfer/strategies/http_strategy.py
covalent/_file_transfer/strategies/rsync_strategy.py
covalent/_file_transfer/strategies/s3_strategy.py
covalent/_file_transfer/strategies/shutil_strategy.py
covalent/_file_transfer/strategies/transfer_strategy_base.py
covalent/_programmatic/__init__.py
covalent/_programmatic/commands.py
covalent/_results_manager/__init__.py
covalent/_results_manager/result.py
covalent/_results_manager/results_manager.py
covalent/_results_manager/utils.py
covalent/_results_manager/wait.py
covalent/_serialize/__init__.py
covalent/_serialize/common.py
covalent/_serialize/electron.py
covalent/_serialize/lattice.py
covalent/_serialize/result.py
covalent/_serialize/transport_graph.py
covalent/_shared_files/__init__.py
covalent/_shared_files/config.py
covalent/_shared_files/context_managers.py
covalent/_shared_files/defaults.py
covalent/_shared_files/exceptions.py
covalent/_shared_files/logger.py
covalent/_shared_files/metrics.py
covalent/_shared_files/pickling.py
covalent/_shared_files/util_classes.py
covalent/_shared_files/utils.py
covalent/_shared_files/schemas/__init__.py
covalent/_shared_files/schemas/asset.py
covalent/_shared_files/schemas/common.py
covalent/_shared_files/schemas/edge.py
covalent/_shared_files/schemas/electron.py
covalent/_shared_files/schemas/lattice.py
