Metadata-Version: 2.1
Name: covalent
Version: 0.238.0
Summary: Covalent Workflow Tool
Home-page: https://github.com/AgnostiqHQ/covalent
Download-URL: https://github.com/AgnostiqHQ/covalent/archive/v0.238.0.tar.gz
Author: Agnostiq
Author-email: support@agnostiq.ai
Maintainer: Agnostiq
License: Apache License 2.0
Classifier: Development Status :: 4 - Beta
Classifier: Environment :: Console
Classifier: Intended Audience :: Developers
Classifier: Intended Audience :: Education
Classifier: Intended Audience :: Science/Research
Classifier: License :: OSI Approved :: Apache Software License
Classifier: Natural Language :: English
Classifier: Operating System :: MacOS :: MacOS X
Classifier: Operating System :: POSIX
Classifier: Programming Language :: Python :: 3
Classifier: Programming Language :: Python :: 3 :: Only
Classifier: Programming Language :: Python :: 3.10
Classifier: Programming Language :: Python :: 3.11
Classifier: Programming Language :: Python :: 3.12
Classifier: Topic :: Adaptive Technologies
Classifier: Topic :: Scientific/Engineering
Classifier: Topic :: Scientific/Engineering :: Interface Engine/Protocol Translator
Classifier: Topic :: Software Development
Classifier: Topic :: System :: Distributed Computing
License-File: LICENSE
Requires-Dist: aiofiles>=0.8.0
Requires-Dist: aiohttp>=3.8.1
Requires-Dist: alembic>=1.8.0
Requires-Dist: boto3>=1.26.110
Requires-Dist: click>=8.1.3
Requires-Dist: cloudpickle>=2.0.0
Requires-Dist: dask[distributed]>=2022.6.0
Requires-Dist: fastapi>=0.100.0
Requires-Dist: filelock>=3.12.2
Requires-Dist: furl>=2.1.3
Requires-Dist: natsort>=8.4.0
Requires-Dist: networkx>=2.8.6
Requires-Dist: psutil>=5.9.0
Requires-Dist: pydantic>=2.1.1
Requires-Dist: python-multipart>=0.0.6
Requires-Dist: python-socketio>=5.7.1
Requires-Dist: requests>=2.24.0
Requires-Dist: rich<=13.3.5,>=12.0.0
Requires-Dist: sqlalchemy<2.0.0,>=1.4.37
Requires-Dist: sqlalchemy_utils>=0.38.3
Requires-Dist: toml>=0.10.2
Requires-Dist: typing-extensions>=4.8.0
Requires-Dist: uvicorn[standard]
Requires-Dist: watchdog>=2.2.1
Provides-Extra: aws
Requires-Dist: boto3>=1.20.48; extra == "aws"
Provides-Extra: azure
Requires-Dist: azure-identity>=1.13.0; extra == "azure"
Requires-Dist: azure-storage-blob>=12.16.0; extra == "azure"
Provides-Extra: braket
Requires-Dist: amazon-braket-pennylane-plugin>=1.17.4; extra == "braket"
Requires-Dist: boto3>=1.28.5; extra == "braket"
Provides-Extra: gcp
Requires-Dist: google-auth>=2.16.2; extra == "gcp"
Requires-Dist: google-cloud-storage>=2.7.0; extra == "gcp"
Provides-Extra: mysql
Requires-Dist: mysqlclient>=2.1.1; extra == "mysql"
Provides-Extra: postgres
Requires-Dist: psycopg2-binary>=2.9.5; extra == "postgres"
Provides-Extra: qiskit
Requires-Dist: pennylane-qiskit==0.30; extra == "qiskit"
Requires-Dist: qiskit==0.43.1; extra == "qiskit"
Requires-Dist: qiskit-ibm-provider==0.6.1; extra == "qiskit"
Requires-Dist: qiskit-ibm-runtime==0.10.0; extra == "qiskit"
